{
  "builder_name": "text",
  "citation": "",
  "config_name": "default",
  "dataset_name": "text",
  "dataset_size": 321545757,
  "description": "",
  "download_checksums": {
    "/Users/thomasmorton/Italian-Model/data/processed/50M/PaCCSS-IT.train": {
      "num_bytes": 2189920,
      "checksum": null
    },
    "/Users/thomasmorton/Italian-Model/data/processed/50M/europarl-v7.it-en.it.train": {
      "num_bytes": 131366671,
      "checksum": null
    },
    "/Users/thomasmorton/Italian-Model/data/processed/50M/CHILDES.train": {
      "num_bytes": 2742211,
      "checksum": null
    },
    "/Users/thomasmorton/Italian-Model/data/processed/50M/Leipzig_Web_Public.train": {
      "num_bytes": 51224878,
      "checksum": null
    },
    "/Users/thomasmorton/Italian-Model/data/processed/50M/CORPUS_ISACCO.train": {
      "num_bytes": 246706,
      "checksum": null
    },
    "/Users/thomasmorton/Italian-Model/data/processed/50M/CltA.train": {
      "num_bytes": 1233882,
      "checksum": null
    },
    "/Users/thomasmorton/Italian-Model/data/processed/50M/SPGC.train": {
      "num_bytes": 102524441,
      "checksum": null
    },
    "/Users/thomasmorton/Italian-Model/data/processed/50M/QCRI.train": {
      "num_bytes": 25091783,
      "checksum": null
    }
  },
  "download_size": 316620492,
  "features": {
    "input_ids": {
      "feature": {
        "dtype": "int32",
        "_type": "Value"
      },
      "_type": "Sequence"
    }
  },
  "homepage": "",
  "license": "",
  "size_in_bytes": 638166249,
  "splits": {
    "train": {
      "name": "train",
      "num_bytes": 321545757,
      "num_examples": 1641755,
      "dataset_name": "text"
    }
  },
  "version": {
    "version_str": "0.0.0",
    "major": 0,
    "minor": 0,
    "patch": 0
  }
}